bm25_vectorizer/__init__.py
bm25_vectorizer-0.0.2.dist-info/licenses/LICENSE
bm25_vectorizer-0.0.2.dist-info/METADATA
bm25_vectorizer-0.0.2.dist-info/WHEEL
bm25_vectorizer-0.0.2.dist-info/top_level.txt
bm25_vectorizer-0.0.2.dist-info/RECORD
