Metadata-Version: 2.4
Name: bm25_vectorizer
Version: 0.0.2
Summary: BM25 Vectorizer (Scikit-learn Compatible)
Author-email: Vladimir Gurevich <imvladikon@gmail.com>
License: MIT
Requires-Python: >=3.10
License-File: LICENSE
Requires-Dist: numpy
Requires-Dist: scipy
Requires-Dist: scikit-learn
Requires-Dist: packaging
Requires-Dist: typing-extensions
Provides-Extra: dev
Requires-Dist: uv; extra == "dev"
Requires-Dist: python-dotenv; extra == "dev"
Requires-Dist: ruff; extra == "dev"
Requires-Dist: mypy; extra == "dev"
Requires-Dist: pre-commit; extra == "dev"
Dynamic: license-file
